LICENSE
setup.py
bayesgm/__init__.py
bayesgm/__main__.py
bayesgm.egg-info/PKG-INFO
bayesgm.egg-info/SOURCES.txt
bayesgm.egg-info/dependency_links.txt
bayesgm.egg-info/entry_points.txt
bayesgm.egg-info/requires.txt
bayesgm.egg-info/top_level.txt
bayesgm/cli/__init__.py
bayesgm/cli/cli.py
bayesgm/datasets/__init__.py
bayesgm/datasets/base_sampler.py
bayesgm/datasets/data_sampler.py
bayesgm/models/__init__.py
bayesgm/models/base.py
bayesgm/models/bayesgm.py
bayesgm/models/causalbgm.py
bayesgm/tests/__init__.py
bayesgm/tests/test_cli.py
bayesgm/tests/test_datasets.py
bayesgm/tests/test_models.py
bayesgm/tests/test_utils.py
bayesgm/utils/__init__.py
bayesgm/utils/data_io.py
bayesgm/utils/helpers.py