Metadata-Version: 2.1
Name: bayesgm
Version: 0.3.0
Summary: An AI-powered Bayesian generative modeling approach
Home-page: https://github.com/SUwonglab/CausalBGM
Author: Qiao Liu
Author-email: liuqiao@stanford.edu
Classifier: Programming Language :: Python :: 3
Classifier: License :: OSI Approved :: MIT License
Classifier: Operating System :: OS Independent
Requires-Python: >=3.7, <3.11
License-File: LICENSE
